jaxabm/__init__.py
jaxabm/agent.py
jaxabm/agentpy.py
jaxabm/analysis.py
jaxabm/api.py
jaxabm/core.py
jaxabm/model.py
jaxabm/utils.py
jaxabm/legacy/__init__.py
jaxabm-0.1.5.dist-info/licenses/LICENSE
tests/__init__.py
tests/conftest.py
tests/run_tests.py
jaxabm-0.1.5.dist-info/METADATA
jaxabm-0.1.5.dist-info/WHEEL
jaxabm-0.1.5.dist-info/top_level.txt
jaxabm-0.1.5.dist-info/RECORD
